aerobulk/mod_aerobulk_wrap.cpython-310-darwin.so
aerobulk_python-0.0.0.dist-info/LICENSE
aerobulk_python-0.0.0.dist-info/METADATA
aerobulk_python-0.0.0.dist-info/WHEEL
aerobulk_python-0.0.0.dist-info/top_level.txt
aerobulk_python-0.0.0.dist-info/RECORD
