Metadata-Version: 2.1
Name: aerobulk-python
Version: 0.0.0
Summary: General Circulation Model Postprocessing with xarray
Home-page: https://github.com/xgcm/aerobulk-python
Author: aerobulk-python Developers
Author-email: julius@ldeo.columbia.edu
License: UNKNOWN
Platform: UNKNOWN
Requires-Python: >=3.7
License-File: LICENSE
Requires-Dist: numpy
